payment_emulation/__init__.py
payment_emulation/__main__.py
payment_emulation/payment/__init__.py
payment_emulation/payment/admin.py
payment_emulation/payment/apps.py
payment_emulation/payment/management/__init__.py
payment_emulation/payment/management/commands/__init__.py
payment_emulation/payment/management/commands/createseeds.py
payment_emulation/payment/management/commands/deleteseeds.py
payment_emulation/payment/management/commands/setbalance.py
payment_emulation/payment/migrations/0001_initial.py
payment_emulation/payment/migrations/0002_insert_seeds.py
payment_emulation/payment/migrations/__init__.py
payment_emulation/payment/models.py
payment_emulation/payment/paymentSDK.py
payment_emulation/utils/__init__.py
payment_emulation/utils/generators.py
payment_emulation-0.1.0.dist-info/entry_points.txt
payment_emulation-0.1.0.dist-info/LICENSE
payment_emulation-0.1.0.dist-info/METADATA
payment_emulation-0.1.0.dist-info/WHEEL
payment_emulation-0.1.0.dist-info/RECORD
