Metadata-Version: 2.3
Name: payment-emulation
Version: 0.1.0
Summary: Uma biblioteca desenvolvida para ser utilizada em projetos Django para emular pagamentos com cartão bancário.
License: MIT License
Keywords: payment,emulation,SDK,implementation,e-commerce,pagamento,emulação,implementação
Author: Valdean
Author-email: valdeanjose6@gmail.com
Requires-Python: >=3.10
Classifier: Framework :: Django
Classifier: Programming Language :: Python :: 3
Classifier: Programming Language :: Python :: 3.10
Classifier: Programming Language :: Python :: 3.11
Classifier: Programming Language :: Python :: 3.12
Classifier: Programming Language :: Python :: 3.13
Classifier: License :: OSI Approved :: MIT License
Classifier: Operating System :: OS Independent
Requires-Dist: django (>=5.1.5,<6.0.0)
Requires-Dist: pycpfcnpj (>=1.8) ; python_version >= "3.8" and python_version < "4.0"
Project-URL: Bug Tracker, https://github.com/valdean7/payment_emulation/issues
Project-URL: Documentation, https://payment-emulation.readthedocs.io/latest/
Project-URL: Repository, https://github.com/valdean7/payment_emulation
